iotdatalog/__init__.py
iotdatalog/api.py
iotdatalog/models.py
iotdatalog-0.1.5.dist-info/LICENSE
iotdatalog-0.1.5.dist-info/METADATA
iotdatalog-0.1.5.dist-info/WHEEL
iotdatalog-0.1.5.dist-info/top_level.txt
iotdatalog-0.1.5.dist-info/RECORD
